MIPS/Main module/ALU.sv
module ALU(input [2:0] ALUControl,
         input[31:0] SrcA,
         input[31:0] SrcB,
         output reg[31:0] ALUResult,
         output reg Zero);
         
    always@(*) begin
        case(ALUControl)
             3'b010: ALUResult = SrcA + SrcB;
             3'b110:begin
                 ALUResult = SrcA - SrcB;
                 Zero = SrcA - SrcB == 0? 1: 0;
             end
             3'b000: ALUResult = SrcA & SrcB;
             3'b001: ALUResult = SrcA | SrcB;
             3'b111: Zero = SrcA - SrcB == 0? 1: 0;
             default: begin
                Zero = 1'bx;
                ALUResult = 32'bx;
             end
        endcase
    end

    

endmodule

MIPS Verilog/Modules/ALU/testbench.sv
module ALU_TB;
  
  reg[2:0] alcontrolt;
  reg[31:0] src1, src2;
  wire [31:0] result;
  wire zero;
  

  
  ALU alu_dut(alcontrolt, src1, src2, result, zero);
  
  initial
    begin
      $dumpfile("dump.vcd");
      $dumpvars(0, alu_dut);
    end
  
//   initial begin
//     #5 clkt = 1'b1;
//     forever #5 clkt =~ clkt;
//   end
  
  initial
    #900 $finish;
  
  
  task write(input [2:0] din);
    begin
      alcontrolt = din;
    end
  endtask

  task writeSources(input [31:0] din1, input [31:0] din2);
    begin
        src1 = din1;
        src2 = din2;
    end
  endtask

  initial begin
    //All tests gave the expected result
    #5 writeSources(32'd17, 32'd10); write(3'b010);//27
    #5 write(3'b110); //7
    #5 write(3'b000); //0
    #5 write(3'b001); //27
    #5 write(3'b111); //Zero = 0;
    #5 write(3'b101); //undefined

    #5 writeSources(32'd10, 32'd10); write(3'b111); //Zero = 1; 




  end
    
    
  
endmodule

MIPS/Modules/ALU/dump.vcd
$date
	Mon Jul 03 16:36:54 2023
$end
$version
	Icarus Verilog
$end
$timescale
	1s
$end
$scope module ALU_TB $end
$scope module alu_dut $end
$var wire 3 ! ALUControl [2:0] $end
$var wire 32 " SrcA [31:0] $end
$var wire 32 # SrcB [31:0] $end
$var reg 32 $ ALUResult [31:0] $end
$var reg 1 % Zero $end
$upscope $end
$upscope $end
$enddefinitions $end
$comment Show the parameter values. $end
$dumpall
$end
#0
$dumpvars
x%
bx $
bx #
bx "
bx !
$end
#5
b11011 $
b10 !
b1010 #
b10001 "
#10
b111 $
b110 !
#15
b0 $
b0 !
#20
b11011 $
b1 !
#25
0%
b111 !
#30
bx $
x%
b101 !
#35
1%
b111 !
b1010 "
