Homeworks/Tema 1/PISO/design.sv
module  PISO(
    input[3:0] din,
    input clk,
    input shift_pl,
    output reg dout  
); 
reg[3:0] data=4'b0;
always@(posedge clk)
    begin
        if(~shift_pl)
            data <= din;
        else
            begin
                data <= {1'b0, data[3:1]};
                dout <= data[0];
            end
    end
    
endmodule

Homeworks/Tema 1/PISO/testbench.sv
module PISO_DUT;
  reg[3:0] dint;
  reg clkt, shift_plt;
  wire doutt;
  
  PISO piso_dut(dint, clkt, shift_plt, doutt);
   initial dint= 4'b1101;
   initial clkt= 1'b0;
   initial shift_plt= 1'b0;
  
  initial forever #5 clkt = ~clkt;
  //initial forever #3 dint = ~dint;


  initial begin
    $dumpfile("dump.vcd");
    $dumpvars(0, piso_dut);
    #6; shift_plt= 1'b1;
    #100;
    $finish(1);
  end
endmodule

Homeworks/Tema 1/PISO/dump.vcd
$date
	Tue Jun 27 23:52:06 2023
$end
$version
	Icarus Verilog
$end
$timescale
	1s
$end
$scope module PISO_DUT $end
$scope module piso_dut $end
$var wire 1 ! clk $end
$var wire 4 " din [3:0] $end
$var wire 1 # shift_pl $end
$var reg 4 $ data [3:0] $end
$var reg 1 % dout $end
$upscope $end
$upscope $end
$enddefinitions $end
$comment Show the parameter values. $end
$dumpall
$end
#0
$dumpvars
x%
b0 $
0#
b1101 "
0!
$end
#5
b1101 $
1!
#6
1#
#10
0!
#15
1%
b110 $
1!
#20
0!
#25
0%
b11 $
1!
#30
0!
#35
1%
b1 $
1!
#40
0!
#45
b0 $
1!
#50
0!
#55
0%
1!
