MIPS/Modules/ALUDec/ALUDec.sv
module ALUDEC(input [1:0] aluop, input [5:0] funct, output reg [2:0] alucontrol);
  always@(*)
    casex({aluop, funct})
      8'b00_xxxxxx: alucontrol = 3'b010; 		//add
      8'bx1_0xxxxx: alucontrol = 3'b110;    //sub
      8'b1x_100000: alucontrol = 3'b010;    //add
      8'b1x_100010: alucontrol = 3'b110; 		//sub
      8'b1x_100100: alucontrol = 3'b0;			//and
      8'b1x_100101: alucontrol = 3'b001;		//or
      8'b1x_101010: alucontrol = 3'b1;			//set less than
    endcase
  
endmodule

MIPS Verilog/Modules/ALUDec/testbench.sv
module stack_TB;
  
  reg[1:0] aluopt;
  reg[5:0] functt;
  wire [2:0] alucontrolt;
  

  
  ALUDEC aludec_dut(aluopt, functt, alucontrolt);
  
  initial
    begin
      $dumpfile("dump.vcd");
      $dumpvars(0, aludec_dut);
    end
  
//   initial begin
//     #5 clkt = 1'b1;
//     forever #5 clkt =~ clkt;
//   end
  
  initial
    #900 $finish;
  
  
  task write(input [7:0] din);
    begin
      aluopt = din[7:6];
      functt = din[5:0];
    end
  endtask
  
  
  initial begin
    #7 write(8'b1x_100000);
    #7 write(8'b1x_100010);
    #7 write(8'bx1_xxxxxx);
    #7 write(8'b00_xxxxxx);
    #7 write(8'b1x_100100);
    #7 write(8'b1x_100101);
    #7 write(8'b1x_101010);



  end
    
    
  
endmodule

MIPS/Modules/ALUDec/dump.vcd
$date
	Sun Jul  2 09:19:58 2023
$end
$version
	Icarus Verilog
$end
$timescale
	1s
$end
$scope module stack_TB $end
$scope module aludec_dut $end
$var wire 2 ! aluop [1:0] $end
$var wire 6 " funct [5:0] $end
$var reg 3 # alucontrol [2:0] $end
$upscope $end
$upscope $end
$enddefinitions $end
#0
$dumpvars
bx #
bx "
bx !
$end
#7
b10 #
b100000 "
b1x !
#14
b110 #
b100010 "
#21
bx "
bx1 !
#28
b10 #
b0 !
#35
b0 #
b100100 "
b1x !
#42
b1 #
b100101 "
#49
b101010 "
