MIPS/Modules/Memory/memory.sv
module INSTRUCTION_MEMORY(
    input [31:0] addr,
    output [31:0] instr
);

    reg [31:0] mem [0:255];
    initial $readmemb("instr.txt", mem);
    assign instr = mem[addr>>2];
   // $display("%d", mem[addr>>2]);
    
endmodule

module DATA_MEMORY(
    input [31:0] din,
    input [31:0] wd,
    input we,
    input clk,
    output [31:0] dout
);
    reg [31:0] mem [0:253];

    assign rd = mem[din>>2];

    always@(posedge clk)
        if(we)
            mem[din>>2] = wd;



endmodule

MIPS/Modules/Memory/testbench.sv
module FileDataReader;

// reg signed [31:0] data[0:7];
//   reg file_open;
//   integer file;
     integer i;

// reg [31:0] addr;
// wire [31:0] instr;

reg [31:0] din, wd;
reg we, clk;
wire [31:0] dout;

//INSTRUCTION_MEMORY im_dut(addr, instr);
DATA_MEMORY dm_dut(din, wd, we, clk, dout);

initial begin
  #0 clk = 1'b0;
  forever #5 clk =~clk;
end

    task write(input [31:0] dint, input [31:0] wdt, input wet);
      begin
        din= dint;
        wd = wdt;
        we = wet;
      end
    endtask

//Populate addresses

// initial begin
//     for (i=0; i<8; i++) begin
//         data[i] = i*4;
//     end
//     $writememb("instr.txt", data);
// end

  // Close file and finish simulation
initial begin
    $dumpfile("dump.vcd"); // Save simulation data in VCD file
    $dumpvars(0, dm_dut);
    for(i = 0; i < 50; i = i + 1)
      $dumpvars(1, dm_dut.mem[i]);
  end

  initial begin
    // #5 addr = 32'h12;
    // #5 addr = 32'h16;
    #3 write(32'd10, 32'd15, 1'b0);
    #20 write(32'd10, 32'd15, 1'b1);
    #100 $finish;
  end

endmodule

MIPS/Modules/Memory/dump.vcd
$date
	Tue Jul 04 22:16:41 2023
$end
$version
	Icarus Verilog
$end
$timescale
	1s
$end
$scope module FileDataReader $end
$scope module dm_dut $end
$var wire 1 ! clk $end
$var wire 32 " din [31:0] $end
$var wire 32 # dout [31:0] $end
$var wire 32 $ wd [31:0] $end
$var wire 1 % we $end
$var wire 1 & rd $end
$upscope $end
$upscope $end
$scope module FileDataReader $end
$scope module dm_dut $end
$var reg 32 ' \mem[0] [31:0] $end
$upscope $end
$upscope $end
$scope module FileDataReader $end
$scope module dm_dut $end
$var reg 32 ( \mem[1] [31:0] $end
$upscope $end
$upscope $end
$scope module FileDataReader $end
$scope module dm_dut $end
$var reg 32 ) \mem[2] [31:0] $end
$upscope $end
$upscope $end
$scope module FileDataReader $end
$scope module dm_dut $end
$var reg 32 * \mem[3] [31:0] $end
$upscope $end
$upscope $end
$scope module FileDataReader $end
$scope module dm_dut $end
$var reg 32 + \mem[4] [31:0] $end
$upscope $end
$upscope $end
$scope module FileDataReader $end
$scope module dm_dut $end
$var reg 32 , \mem[5] [31:0] $end
$upscope $end
$upscope $end
$scope module FileDataReader $end
$scope module dm_dut $end
$var reg 32 - \mem[6] [31:0] $end
$upscope $end
$upscope $end
$scope module FileDataReader $end
$scope module dm_dut $end
$var reg 32 . \mem[7] [31:0] $end
$upscope $end
$upscope $end
$scope module FileDataReader $end
$scope module dm_dut $end
$var reg 32 / \mem[8] [31:0] $end
$upscope $end
$upscope $end
$scope module FileDataReader $end
$scope module dm_dut $end
$var reg 32 0 \mem[9] [31:0] $end
$upscope $end
$upscope $end
$scope module FileDataReader $end
$scope module dm_dut $end
$var reg 32 1 \mem[10] [31:0] $end
$upscope $end
$upscope $end
$scope module FileDataReader $end
$scope module dm_dut $end
$var reg 32 2 \mem[11] [31:0] $end
$upscope $end
$upscope $end
$scope module FileDataReader $end
$scope module dm_dut $end
$var reg 32 3 \mem[12] [31:0] $end
$upscope $end
$upscope $end
$scope module FileDataReader $end
$scope module dm_dut $end
$var reg 32 4 \mem[13] [31:0] $end
$upscope $end
$upscope $end
$scope module FileDataReader $end
$scope module dm_dut $end
$var reg 32 5 \mem[14] [31:0] $end
$upscope $end
$upscope $end
$scope module FileDataReader $end
$scope module dm_dut $end
$var reg 32 6 \mem[15] [31:0] $end
$upscope $end
$upscope $end
$scope module FileDataReader $end
$scope module dm_dut $end
$var reg 32 7 \mem[16] [31:0] $end
$upscope $end
$upscope $end
$scope module FileDataReader $end
$scope module dm_dut $end
$var reg 32 8 \mem[17] [31:0] $end
$upscope $end
$upscope $end
$scope module FileDataReader $end
$scope module dm_dut $end
$var reg 32 9 \mem[18] [31:0] $end
$upscope $end
$upscope $end
$scope module FileDataReader $end
$scope module dm_dut $end
$var reg 32 : \mem[19] [31:0] $end
$upscope $end
$upscope $end
$scope module FileDataReader $end
$scope module dm_dut $end
$var reg 32 ; \mem[20] [31:0] $end
$upscope $end
$upscope $end
$scope module FileDataReader $end
$scope module dm_dut $end
$var reg 32 < \mem[21] [31:0] $end
$upscope $end
$upscope $end
$scope module FileDataReader $end
$scope module dm_dut $end
$var reg 32 = \mem[22] [31:0] $end
$upscope $end
$upscope $end
$scope module FileDataReader $end
$scope module dm_dut $end
$var reg 32 > \mem[23] [31:0] $end
$upscope $end
$upscope $end
$scope module FileDataReader $end
$scope module dm_dut $end
$var reg 32 ? \mem[24] [31:0] $end
$upscope $end
$upscope $end
$scope module FileDataReader $end
$scope module dm_dut $end
$var reg 32 @ \mem[25] [31:0] $end
$upscope $end
$upscope $end
$scope module FileDataReader $end
$scope module dm_dut $end
$var reg 32 A \mem[26] [31:0] $end
$upscope $end
$upscope $end
$scope module FileDataReader $end
$scope module dm_dut $end
$var reg 32 B \mem[27] [31:0] $end
$upscope $end
$upscope $end
$scope module FileDataReader $end
$scope module dm_dut $end
$var reg 32 C \mem[28] [31:0] $end
$upscope $end
$upscope $end
$scope module FileDataReader $end
$scope module dm_dut $end
$var reg 32 D \mem[29] [31:0] $end
$upscope $end
$upscope $end
$scope module FileDataReader $end
$scope module dm_dut $end
$var reg 32 E \mem[30] [31:0] $end
$upscope $end
$upscope $end
$scope module FileDataReader $end
$scope module dm_dut $end
$var reg 32 F \mem[31] [31:0] $end
$upscope $end
$upscope $end
$scope module FileDataReader $end
$scope module dm_dut $end
$var reg 32 G \mem[32] [31:0] $end
$upscope $end
$upscope $end
$scope module FileDataReader $end
$scope module dm_dut $end
$var reg 32 H \mem[33] [31:0] $end
$upscope $end
$upscope $end
$scope module FileDataReader $end
$scope module dm_dut $end
$var reg 32 I \mem[34] [31:0] $end
$upscope $end
$upscope $end
$scope module FileDataReader $end
$scope module dm_dut $end
$var reg 32 J \mem[35] [31:0] $end
$upscope $end
$upscope $end
$scope module FileDataReader $end
$scope module dm_dut $end
$var reg 32 K \mem[36] [31:0] $end
$upscope $end
$upscope $end
$scope module FileDataReader $end
$scope module dm_dut $end
$var reg 32 L \mem[37] [31:0] $end
$upscope $end
$upscope $end
$scope module FileDataReader $end
$scope module dm_dut $end
$var reg 32 M \mem[38] [31:0] $end
$upscope $end
$upscope $end
$scope module FileDataReader $end
$scope module dm_dut $end
$var reg 32 N \mem[39] [31:0] $end
$upscope $end
$upscope $end
$scope module FileDataReader $end
$scope module dm_dut $end
$var reg 32 O \mem[40] [31:0] $end
$upscope $end
$upscope $end
$scope module FileDataReader $end
$scope module dm_dut $end
$var reg 32 P \mem[41] [31:0] $end
$upscope $end
$upscope $end
$scope module FileDataReader $end
$scope module dm_dut $end
$var reg 32 Q \mem[42] [31:0] $end
$upscope $end
$upscope $end
$scope module FileDataReader $end
$scope module dm_dut $end
$var reg 32 R \mem[43] [31:0] $end
$upscope $end
$upscope $end
$scope module FileDataReader $end
$scope module dm_dut $end
$var reg 32 S \mem[44] [31:0] $end
$upscope $end
$upscope $end
$scope module FileDataReader $end
$scope module dm_dut $end
$var reg 32 T \mem[45] [31:0] $end
$upscope $end
$upscope $end
$scope module FileDataReader $end
$scope module dm_dut $end
$var reg 32 U \mem[46] [31:0] $end
$upscope $end
$upscope $end
$scope module FileDataReader $end
$scope module dm_dut $end
$var reg 32 V \mem[47] [31:0] $end
$upscope $end
$upscope $end
$scope module FileDataReader $end
$scope module dm_dut $end
$var reg 32 W \mem[48] [31:0] $end
$upscope $end
$upscope $end
$scope module FileDataReader $end
$scope module dm_dut $end
$var reg 32 X \mem[49] [31:0] $end
$upscope $end
$upscope $end
$enddefinitions $end
$comment Show the parameter values. $end
$dumpall
$end
#0
$dumpvars
bx X
bx W
bx V
bx U
bx T
bx S
bx R
bx Q
bx P
bx O
bx N
bx M
bx L
bx K
bx J
bx I
bx H
bx G
bx F
bx E
bx D
bx C
bx B
bx A
bx @
bx ?
bx >
bx =
bx <
bx ;
bx :
bx 9
bx 8
bx 7
bx 6
bx 5
bx 4
bx 3
bx 2
bx 1
bx 0
bx /
bx .
bx -
bx ,
bx +
bx *
bx )
bx (
bx '
x&
x%
bx $
bz #
bx "
0!
$end
#3
0%
b1111 $
b1010 "
#5
1!
#10
0!
#15
1!
#20
0!
#23
1%
#25
1&
b1111 )
1!
#30
0!
#35
b1111 )
1!
#40
0!
#45
b1111 )
1!
#50
0!
#55
b1111 )
1!
#60
0!
#65
b1111 )
1!
#70
0!
#75
b1111 )
1!
#80
0!
#85
b1111 )
1!
#90
0!
#95
b1111 )
1!
#100
0!
#105
b1111 )
1!
#110
0!
#115
b1111 )
1!
